genome_seq_finder/__main__.py
genome_seq_finder/lib/__init__.py
genome_seq_finder/lib/file.py
genome_seq_finder/lib/seq_finder.py
genome_seq_finder/lib/types.py
genome_seq_finder/main.py
genome_seq_finder-0.1.0.dist-info/WHEEL
genome_seq_finder-0.1.0.dist-info/entry_points.txt
genome_seq_finder-0.1.0.dist-info/METADATA
genome_seq_finder-0.1.0.dist-info/RECORD
